task_view/__init__.py
task_view/log.py
task_view/utils.py
task_view/server/__init__.py
task_view/server/__main__.py
task_view/server/mcp/__init__.py
task_view/server/mcp/content.py
task_view/server/mcp/math.py
task_view/server/mcp/mcp.py
task_view/server/mcp/resource.py
task_view/server/mcp/weather.py
task_view/server/models/__init__.py
task_view/server/models/models.py
task_view/server/routers/__init__.py
task_view/server/routers/admin.py
task_view/server/routers/user.py
task_view/server/utils/__init__.py
task_view/server/utils/auth_backends.py
task_view/server/utils/database.py
task_view/server/utils/user_manager.py
task_view-0.1.1.dist-info/METADATA
task_view-0.1.1.dist-info/WHEEL
task_view-0.1.1.dist-info/top_level.txt
task_view-0.1.1.dist-info/RECORD
